<?xml version="1.0" encoding="ascii"?>
<p:sld xmlns:a="http://schemas.openxmlformats.org/drawingml/2006/main" xmlns:r="http://schemas.openxmlformats.org/officeDocument/2006/relationships" xmlns:p="http://schemas.openxmlformats.org/presentationml/2006/main">
  <p:cSld>
    <p:bg>
      <p:bgPr>
        <a:solidFill>
          <a:srgbClr val="FAF9F5"/>
        </a:solidFill>
        <a:effectLst/>
      </p:bgPr>
    </p:bg>
    <p:spTree>
      <p:nvGrpSpPr>
        <p:cNvPr id="1" name="Shape 15"/>
        <p:cNvGrpSpPr/>
        <p:nvPr/>
      </p:nvGrpSpPr>
      <p:grpSpPr>
        <a:xfrm>
          <a:off x="0" y="0"/>
          <a:ext cx="0" cy="0"/>
          <a:chOff x="0" y="0"/>
          <a:chExt cx="0" cy="0"/>
        </a:xfrm>
      </p:grpSpPr><p:pic xmlns:a="http://schemas.openxmlformats.org/drawingml/2006/main" xmlns:r="http://schemas.openxmlformats.org/officeDocument/2006/relationships" xmlns:p="http://schemas.openxmlformats.org/presentationml/2006/main">
        <p:nvPicPr><p:cNvPr id="9999" name="DASH Logo"/><p:cNvPicPr/><p:nvPr/></p:nvPicPr>
        <p:blipFill><a:blip r:embed="rId6"/><a:stretch><a:fillRect/></a:stretch></p:blipFill>
        <p:spPr>
          <a:xfrm><a:off x="300000" y="150000"/><a:ext cx="1371600" cy="301752"/></a:xfrm>
          <a:prstGeom prst="rect"><a:avLst/></a:prstGeom>
        </p:spPr>
      </p:pic>
      <p:pic>
        <p:nvPicPr>
          <p:cNvPr id="9999" name="DASH Logo"/>
          <p:cNvPicPr/>
          <p:nvPr/>
        </p:nvPicPr>
        <p:blipFill>
          <a:blip r:embed="rId3"/>
          <a:stretch>
            <a:fillRect/>
          </a:stretch>
        </p:blipFill>
        <p:spPr>
          <a:xfrm>
            <a:off x="350000" y="150000"/>
            <a:ext cx="1449000" cy="320000"/>
          </a:xfrm>
          <a:prstGeom prst="rect">
            <a:avLst/>
          </a:prstGeom>
        </p:spPr>
      </p:pic>
      <p:sp>
        <p:nvSpPr>
          <p:cNvPr id="16" name="Google Shape;16;p1"/>
          <p:cNvSpPr/>
          <p:nvPr/>
        </p:nvSpPr>
        <p:spPr>
          <a:xfrm>
            <a:off x="7796212" y="3762375"/>
            <a:ext cx="2171700" cy="2171700"/>
          </a:xfrm>
          <a:prstGeom prst="ellipse">
            <a:avLst/>
          </a:prstGeom>
          <a:solidFill>
            <a:srgbClr val="FFC53D"/>
          </a:solidFill>
          <a:ln>
            <a:noFill/>
          </a:ln>
        </p:spPr>
        <p:txBody>
          <a:bodyPr spcFirstLastPara="1" wrap="square" lIns="91425" tIns="45700" rIns="91425" bIns="45700" anchor="ctr" anchorCtr="0">
            <a:noAutofit/>
          </a:bodyPr>
          <a:lstStyle/>
          <a:p>
            <a:pPr marL="0" marR="0" lvl="0" indent="0" algn="l" rtl="0">
              <a:spcBef>
                <a:spcPts val="0"/>
              </a:spcBef>
              <a:spcAft>
                <a:spcPts val="0"/>
              </a:spcAft>
              <a:buClr>
                <a:schemeClr val="dk1"/>
              </a:buClr>
              <a:buSzPts val="1800"/>
              <a:buFont typeface="Calibri"/>
              <a:buNone/>
            </a:pPr>
            <a:endParaRPr sz="1800" b="0" i="0" u="none" strike="noStrike" cap="none">
              <a:solidFill>
                <a:schemeClr val="dk1"/>
              </a:solidFill>
              <a:latin typeface="Calibri"/>
              <a:ea typeface="Calibri"/>
              <a:cs typeface="Calibri"/>
              <a:sym typeface="Calibri"/>
            </a:endParaRPr>
          </a:p>
        </p:txBody>
      </p:sp>
      <p:sp>
        <p:nvSpPr>
          <p:cNvPr id="17" name="Google Shape;17;p1"/>
          <p:cNvSpPr/>
          <p:nvPr/>
        </p:nvSpPr>
        <p:spPr>
          <a:xfrm>
            <a:off x="-471487" y="2185988"/>
            <a:ext cx="1895475" cy="1895475"/>
          </a:xfrm>
          <a:prstGeom prst="ellipse">
            <a:avLst/>
          </a:prstGeom>
          <a:solidFill>
            <a:srgbClr val="2DABC2"/>
          </a:solidFill>
          <a:ln>
            <a:noFill/>
          </a:ln>
        </p:spPr>
        <p:txBody>
          <a:bodyPr spcFirstLastPara="1" wrap="square" lIns="91425" tIns="45700" rIns="91425" bIns="45700" anchor="ctr" anchorCtr="0">
            <a:noAutofit/>
          </a:bodyPr>
          <a:lstStyle/>
          <a:p>
            <a:pPr marL="0" marR="0" lvl="0" indent="0" algn="l" rtl="0">
              <a:spcBef>
                <a:spcPts val="0"/>
              </a:spcBef>
              <a:spcAft>
                <a:spcPts val="0"/>
              </a:spcAft>
              <a:buClr>
                <a:schemeClr val="dk1"/>
              </a:buClr>
              <a:buSzPts val="1800"/>
              <a:buFont typeface="Calibri"/>
              <a:buNone/>
            </a:pPr>
            <a:endParaRPr sz="1800" b="0" i="0" u="none" strike="noStrike" cap="none">
              <a:solidFill>
                <a:schemeClr val="dk1"/>
              </a:solidFill>
              <a:latin typeface="Calibri"/>
              <a:ea typeface="Calibri"/>
              <a:cs typeface="Calibri"/>
              <a:sym typeface="Calibri"/>
            </a:endParaRPr>
          </a:p>
        </p:txBody>
      </p:sp>
      <p:sp>
        <p:nvSpPr>
          <p:cNvPr id="18" name="Google Shape;18;p1"/>
          <p:cNvSpPr/>
          <p:nvPr/>
        </p:nvSpPr>
        <p:spPr>
          <a:xfrm>
            <a:off x="476250" y="1166813"/>
            <a:ext cx="8191500" cy="2571750"/>
          </a:xfrm>
          <a:prstGeom prst="rect">
            <a:avLst/>
          </a:prstGeom>
          <a:noFill/>
          <a:ln>
            <a:noFill/>
          </a:ln>
        </p:spPr>
        <p:txBody>
          <a:bodyPr spcFirstLastPara="1" wrap="square" lIns="0" tIns="0" rIns="0" bIns="0" anchor="ctr" anchorCtr="0">
            <a:noAutofit/>
          </a:bodyPr>
          <a:lstStyle/>
          <a:p>
            <a:pPr marL="0" marR="0" lvl="0" indent="0" algn="ctr" rtl="0">
              <a:lnSpc>
                <a:spcPct val="89998"/>
              </a:lnSpc>
              <a:spcBef>
                <a:spcPts val="0"/>
              </a:spcBef>
              <a:spcAft>
                <a:spcPts val="0"/>
              </a:spcAft>
              <a:buClr>
                <a:srgbClr val="000000"/>
              </a:buClr>
              <a:buSzPts val="10688"/>
              <a:buFont typeface="Neuton"/>
              <a:buNone/>
            </a:pPr>
            <a:r>
              <a:rPr lang="en-US" sz="8800" u="none" strike="noStrike" cap="none" dirty="0">
                <a:solidFill>
                  <a:srgbClr val="000000"/>
                </a:solidFill>
                <a:latin typeface="Neuton"/>
                <a:ea typeface="Batang" panose="02030600000101010101" pitchFamily="18" charset="-127"/>
                <a:cs typeface="Neuton"/>
                <a:sym typeface="Neuton"/>
              </a:rPr>
              <a:t>Dash</a:t>
            </a:r>
            <a:endParaRPr sz="8800" u="none" strike="noStrike" cap="none" dirty="0">
              <a:solidFill>
                <a:schemeClr val="dk1"/>
              </a:solidFill>
              <a:latin typeface="Calibri"/>
              <a:ea typeface="Batang" panose="02030600000101010101" pitchFamily="18" charset="-127"/>
              <a:cs typeface="Calibri"/>
              <a:sym typeface="Calibri"/>
            </a:endParaRPr>
          </a:p>
          <a:p>
            <a:pPr marL="0" marR="0" lvl="0" indent="0" algn="ctr" rtl="0">
              <a:lnSpc>
                <a:spcPct val="89998"/>
              </a:lnSpc>
              <a:spcBef>
                <a:spcPts val="0"/>
              </a:spcBef>
              <a:spcAft>
                <a:spcPts val="0"/>
              </a:spcAft>
              <a:buClr>
                <a:srgbClr val="000000"/>
              </a:buClr>
              <a:buSzPts val="10688"/>
              <a:buFont typeface="Neuton"/>
              <a:buNone/>
            </a:pPr>
            <a:r>
              <a:rPr lang="en-US" sz="8800" u="none" strike="noStrike" cap="none" dirty="0">
                <a:solidFill>
                  <a:srgbClr val="000000"/>
                </a:solidFill>
                <a:latin typeface="Neuton"/>
                <a:ea typeface="Batang" panose="02030600000101010101" pitchFamily="18" charset="-127"/>
                <a:cs typeface="Neuton"/>
                <a:sym typeface="Neuton"/>
              </a:rPr>
              <a:t>Persona</a:t>
            </a:r>
            <a:endParaRPr sz="8800" u="none" strike="noStrike" cap="none" dirty="0">
              <a:solidFill>
                <a:schemeClr val="dk1"/>
              </a:solidFill>
              <a:latin typeface="Calibri"/>
              <a:ea typeface="Batang" panose="02030600000101010101" pitchFamily="18" charset="-127"/>
              <a:cs typeface="Calibri"/>
              <a:sym typeface="Calibri"/>
            </a:endParaRPr>
          </a:p>
        </p:txBody>
      </p:sp>
      <p:sp>
        <p:nvSpPr>
          <p:cNvPr id="19" name="Google Shape;19;p1"/>
          <p:cNvSpPr/>
          <p:nvPr/>
        </p:nvSpPr>
        <p:spPr>
          <a:xfrm>
            <a:off x="3990975" y="-933450"/>
            <a:ext cx="1866900" cy="1866900"/>
          </a:xfrm>
          <a:prstGeom prst="ellipse">
            <a:avLst/>
          </a:prstGeom>
          <a:solidFill>
            <a:srgbClr val="FFC53D"/>
          </a:solidFill>
          <a:ln>
            <a:noFill/>
          </a:ln>
        </p:spPr>
        <p:txBody>
          <a:bodyPr spcFirstLastPara="1" wrap="square" lIns="91425" tIns="45700" rIns="91425" bIns="45700" anchor="ctr" anchorCtr="0">
            <a:noAutofit/>
          </a:bodyPr>
          <a:lstStyle/>
          <a:p>
            <a:pPr marL="0" marR="0" lvl="0" indent="0" algn="l" rtl="0">
              <a:spcBef>
                <a:spcPts val="0"/>
              </a:spcBef>
              <a:spcAft>
                <a:spcPts val="0"/>
              </a:spcAft>
              <a:buClr>
                <a:schemeClr val="dk1"/>
              </a:buClr>
              <a:buSzPts val="1800"/>
              <a:buFont typeface="Calibri"/>
              <a:buNone/>
            </a:pPr>
            <a:endParaRPr sz="1800" b="0" i="0" u="none" strike="noStrike" cap="none">
              <a:solidFill>
                <a:schemeClr val="dk1"/>
              </a:solidFill>
              <a:latin typeface="Calibri"/>
              <a:ea typeface="Calibri"/>
              <a:cs typeface="Calibri"/>
              <a:sym typeface="Calibri"/>
            </a:endParaRPr>
          </a:p>
        </p:txBody>
      </p:sp>
      <p:sp>
        <p:nvSpPr>
          <p:cNvPr id="21" name="Google Shape;21;p1"/>
          <p:cNvSpPr/>
          <p:nvPr/>
        </p:nvSpPr>
        <p:spPr>
          <a:xfrm>
            <a:off x="476250" y="4595813"/>
            <a:ext cx="628650" cy="114300"/>
          </a:xfrm>
          <a:prstGeom prst="rect">
            <a:avLst/>
          </a:prstGeom>
          <a:noFill/>
          <a:ln>
            <a:noFill/>
          </a:ln>
        </p:spPr>
        <p:txBody>
          <a:bodyPr spcFirstLastPara="1" wrap="square" lIns="0" tIns="0" rIns="0" bIns="0" anchor="ctr" anchorCtr="0">
            <a:noAutofit/>
          </a:bodyPr>
          <a:lstStyle/>
          <a:p>
            <a:pPr marL="0" marR="0" lvl="0" indent="0" algn="l" rtl="0">
              <a:lnSpc>
                <a:spcPct val="119915"/>
              </a:lnSpc>
              <a:spcBef>
                <a:spcPts val="0"/>
              </a:spcBef>
              <a:spcAft>
                <a:spcPts val="0"/>
              </a:spcAft>
              <a:buClr>
                <a:srgbClr val="000000"/>
              </a:buClr>
              <a:buSzPts val="713"/>
              <a:buFont typeface="Open Sans"/>
              <a:buNone/>
            </a:pPr>
            <a:r>
              <a:rPr lang="en-US" sz="713" b="1" i="0" u="none" strike="noStrike" cap="none" dirty="0">
                <a:solidFill>
                  <a:srgbClr val="000000"/>
                </a:solidFill>
                <a:latin typeface="Open Sans"/>
                <a:ea typeface="Open Sans"/>
                <a:cs typeface="Open Sans"/>
                <a:sym typeface="Open Sans"/>
              </a:rPr>
              <a:t>Creator Intelligence Engine</a:t>
            </a:r>
            <a:endParaRPr sz="713" b="0" i="0" u="none" strike="noStrike" cap="none" dirty="0">
              <a:solidFill>
                <a:schemeClr val="dk1"/>
              </a:solidFill>
              <a:latin typeface="Calibri"/>
              <a:ea typeface="Calibri"/>
              <a:cs typeface="Calibri"/>
              <a:sym typeface="Calibri"/>
            </a:endParaRPr>
          </a:p>
        </p:txBody>
      </p:sp>
      <p:sp>
        <p:nvSpPr>
          <p:cNvPr id="22" name="Google Shape;22;p1"/>
          <p:cNvSpPr/>
          <p:nvPr/>
        </p:nvSpPr>
        <p:spPr>
          <a:xfrm>
            <a:off x="8181975" y="219075"/>
            <a:ext cx="471488" cy="114300"/>
          </a:xfrm>
          <a:prstGeom prst="rect">
            <a:avLst/>
          </a:prstGeom>
          <a:noFill/>
          <a:ln>
            <a:noFill/>
          </a:ln>
        </p:spPr>
        <p:txBody>
          <a:bodyPr spcFirstLastPara="1" wrap="square" lIns="0" tIns="0" rIns="0" bIns="0" anchor="ctr" anchorCtr="0">
            <a:noAutofit/>
          </a:bodyPr>
          <a:lstStyle/>
          <a:p>
            <a:pPr marL="0" marR="0" lvl="0" indent="0" algn="r" rtl="0">
              <a:lnSpc>
                <a:spcPct val="119915"/>
              </a:lnSpc>
              <a:spcBef>
                <a:spcPts val="0"/>
              </a:spcBef>
              <a:spcAft>
                <a:spcPts val="0"/>
              </a:spcAft>
              <a:buClr>
                <a:srgbClr val="000000"/>
              </a:buClr>
              <a:buSzPts val="713"/>
              <a:buFont typeface="Open Sans"/>
              <a:buNone/>
            </a:pPr>
            <a:r>
              <a:rPr lang="en-US" sz="713" b="1" i="0" u="none" strike="noStrike" cap="none">
                <a:solidFill>
                  <a:srgbClr val="000000"/>
                </a:solidFill>
                <a:latin typeface="Open Sans"/>
                <a:ea typeface="Open Sans"/>
                <a:cs typeface="Open Sans"/>
                <a:sym typeface="Open Sans"/>
              </a:rPr>
              <a:t>APR 2026</a:t>
            </a:r>
            <a:endParaRPr sz="713" b="0" i="0" u="none" strike="noStrike" cap="none">
              <a:solidFill>
                <a:schemeClr val="dk1"/>
              </a:solidFill>
              <a:latin typeface="Calibri"/>
              <a:ea typeface="Calibri"/>
              <a:cs typeface="Calibri"/>
              <a:sym typeface="Calibri"/>
            </a:endParaRPr>
          </a:p>
        </p:txBody>
      </p:sp>
      <p:pic>
        <p:nvPicPr>
          <p:cNvPr id="23" name="Google Shape;23;p1" descr="preencoded.png"/>
          <p:cNvPicPr preferRelativeResize="0"/>
          <p:nvPr/>
        </p:nvPicPr>
        <p:blipFill rotWithShape="1">
          <a:blip r:embed="rId4">
            <a:alphaModFix/>
          </a:blip>
          <a:srcRect/>
          <a:stretch/>
        </p:blipFill>
        <p:spPr>
          <a:xfrm>
            <a:off x="7456765" y="4538663"/>
            <a:ext cx="1197293" cy="228600"/>
          </a:xfrm>
          <a:prstGeom prst="rect">
            <a:avLst/>
          </a:prstGeom>
          <a:noFill/>
          <a:ln>
            <a:noFill/>
          </a:ln>
        </p:spPr>
      </p:pic>
      <p:pic>
        <p:nvPicPr>
          <p:cNvPr id="2" name="DASH Logo">
            <a:extLst>
              <a:ext uri="{FF2B5EF4-FFF2-40B4-BE49-F238E27FC236}">
                <a16:creationId xmlns:a16="http://schemas.microsoft.com/office/drawing/2014/main" id="{B6D9202C-400F-9367-A596-08863C1C104C}"/>
              </a:ext>
            </a:extLst>
          </p:cNvPr>
          <p:cNvPicPr/>
          <p:nvPr/>
        </p:nvPicPr>
        <p:blipFill>
          <a:blip r:embed="rId5"/>
          <a:stretch>
            <a:fillRect/>
          </a:stretch>
        </p:blipFill>
        <p:spPr>
          <a:xfrm>
            <a:off x="350000" y="149899"/>
            <a:ext cx="1449000" cy="320000"/>
          </a:xfrm>
          <a:prstGeom prst="rect">
            <a:avLst/>
          </a:prstGeom>
        </p:spPr>
      </p:pic>
    </p:spTree>
  </p:cSld>
  <p:clrMapOvr>
    <a:masterClrMapping/>
  </p:clrMapOvr>
</p:sld>
